setup.py
dsnd_distributions96/Binomialdistribution.py
dsnd_distributions96/Gaussiandistribution.py
dsnd_distributions96/Generaldistribution.py
dsnd_distributions96/__init__.py
dsnd_distributions96.egg-info/PKG-INFO
dsnd_distributions96.egg-info/SOURCES.txt
dsnd_distributions96.egg-info/dependency_links.txt
dsnd_distributions96.egg-info/not-zip-safe
dsnd_distributions96.egg-info/top_level.txt